src/__init__.py
src/cli.py
src/packaging/__init__.py
src/packaging/create_package.py
pykaging-0.6.7.dist-info/LICENSE.md
pykaging-0.6.7.dist-info/METADATA
pykaging-0.6.7.dist-info/WHEEL
pykaging-0.6.7.dist-info/entry_points.txt
pykaging-0.6.7.dist-info/top_level.txt
pykaging-0.6.7.dist-info/RECORD
